arrowpython/__init__.py
arrowpython-0.0.4.dist-info/LICENSE
arrowpython-0.0.4.dist-info/METADATA
arrowpython-0.0.4.dist-info/WHEEL
arrowpython-0.0.4.dist-info/top_level.txt
arrowpython-0.0.4.dist-info/RECORD
