Metadata-Version: 2.1
Name: arrowpython
Version: 0.0.4
Summary: A programming language that transpiles to python. It has extremely similar syntax, but instead of colons (:), you use arrows (=>). Along with this, you are also able to call functions with only one argument with special syntax.
Author: RadioactiveRocket
Classifier: Programming Language :: Python :: 3
Classifier: License :: OSI Approved :: MIT License
Classifier: Operating System :: OS Independent
Requires-Python: >=3.7
License-File: LICENSE
